diacalculator/__init__.py
diacalculator/calculator.py
diacalculator-0.0.2.dist-info/LICENSE
diacalculator-0.0.2.dist-info/METADATA
diacalculator-0.0.2.dist-info/WHEEL
diacalculator-0.0.2.dist-info/top_level.txt
diacalculator-0.0.2.dist-info/RECORD
