Metadata-Version: 2.1
Name: diacalculator
Version: 0.0.2
Summary: This is very basic calculator
Author: Nazmul Haque
Author-email: nazmul@daffodil.ac
Classifier: Programming Language :: Python :: 3
Classifier: License :: OSI Approved :: MIT License
Classifier: Operating System :: OS Independent
License-File: LICENSE
